README.md
setup.py
bin/tulip
tuliptask/__init__.py
tuliptask/proc.py
tuliptask/tasks.py
tuliptask/utils.py
tuliptask.egg-info/PKG-INFO
tuliptask.egg-info/SOURCES.txt
tuliptask.egg-info/dependency_links.txt
tuliptask.egg-info/top_level.txt