Metadata-Version: 2.1
Name: tuliptask
Version: 0.0.2
Summary: Simple task runner for applications set up with docker and kubernetes
Home-page: https://github.com/pzmosquito/tuliptask
Author: Peter Zhang
Author-email: pzmosquito@gmail.com
License: MIT License
Platform: UNKNOWN
Classifier: Environment :: Console
Classifier: Intended Audience :: Developers
Classifier: License :: OSI Approved :: MIT License
Classifier: Operating System :: OS Independent
Classifier: Programming Language :: Python
Classifier: Programming Language :: Python :: 3.5
Classifier: Programming Language :: Python :: 3.6
Classifier: Programming Language :: Python :: 3.7
